swastikai/__init__.py
swastikai/memory.py
swastikai/memory_async.py
swastikai/memory_models.py
swastikai/utils.py
tests/__init__.py
tests/test.py
tests/test_async.py
swastikai-1.0.6.dist-info/LICENSE
swastikai-1.0.6.dist-info/METADATA
swastikai-1.0.6.dist-info/WHEEL
swastikai-1.0.6.dist-info/top_level.txt
swastikai-1.0.6.dist-info/RECORD
