Metadata-Version: 2.1
Name: swastikai
Version: 1.0.6
Summary: Official Python SDK for SwastikAI API
Home-page: https://github.com/SwastikAI/swastikai-python-sdk
Author: SwastikAI
Author-email: contact@swastikai.com
License: UNKNOWN
Platform: UNKNOWN
Requires-Python: >=3.9.12
License-File: LICENSE
Requires-Dist: requests>=2.32.3
Requires-Dist: pydantic>=2.9.2
